ShenruqianchuNodeJsInfoqMiniShu/README.md
ShenruqianchuNodeJsInfoqMiniShu/__init__.py
ShenruqianchuNodeJsInfoqMiniShu/__main__.py
ShenruqianchuNodeJsInfoqMiniShu/file.epub
ShenruqianchuNodeJsInfoqMiniShu/index.html
ShenruqianchuNodeJsInfoqMiniShu/css/__init__.py
ShenruqianchuNodeJsInfoqMiniShu/css/annotations.css
ShenruqianchuNodeJsInfoqMiniShu/css/main.css
ShenruqianchuNodeJsInfoqMiniShu/css/normalize.css
ShenruqianchuNodeJsInfoqMiniShu/css/popup.css
ShenruqianchuNodeJsInfoqMiniShu/font/__init__.py
ShenruqianchuNodeJsInfoqMiniShu/font/fontello.eot
ShenruqianchuNodeJsInfoqMiniShu/font/fontello.svg
ShenruqianchuNodeJsInfoqMiniShu/font/fontello.ttf
ShenruqianchuNodeJsInfoqMiniShu/font/fontello.woff
ShenruqianchuNodeJsInfoqMiniShu/img/__init__.py
ShenruqianchuNodeJsInfoqMiniShu/img/annotator-glyph-sprite.png
ShenruqianchuNodeJsInfoqMiniShu/img/annotator-icon-sprite.png
ShenruqianchuNodeJsInfoqMiniShu/img/apple-touch-icon.png
ShenruqianchuNodeJsInfoqMiniShu/img/cancelfullscreen.png
ShenruqianchuNodeJsInfoqMiniShu/img/close.png
ShenruqianchuNodeJsInfoqMiniShu/img/fullscreen.png
ShenruqianchuNodeJsInfoqMiniShu/img/loader.gif
ShenruqianchuNodeJsInfoqMiniShu/img/menu-icon.png
ShenruqianchuNodeJsInfoqMiniShu/img/save.png
ShenruqianchuNodeJsInfoqMiniShu/img/saved.png
ShenruqianchuNodeJsInfoqMiniShu/img/settings-s.png
ShenruqianchuNodeJsInfoqMiniShu/img/settings.png
ShenruqianchuNodeJsInfoqMiniShu/img/star.png
ShenruqianchuNodeJsInfoqMiniShu/js/__init__.py
ShenruqianchuNodeJsInfoqMiniShu/js/epub.js
ShenruqianchuNodeJsInfoqMiniShu/js/epub.min.js
ShenruqianchuNodeJsInfoqMiniShu/js/epub.min.map
ShenruqianchuNodeJsInfoqMiniShu/js/hooks.min.js
ShenruqianchuNodeJsInfoqMiniShu/js/hooks.min.map
ShenruqianchuNodeJsInfoqMiniShu/js/reader.js
ShenruqianchuNodeJsInfoqMiniShu/js/reader.js.map
ShenruqianchuNodeJsInfoqMiniShu/js/reader.min.js
ShenruqianchuNodeJsInfoqMiniShu/js/reader.min.map
ShenruqianchuNodeJsInfoqMiniShu/js/hooks/__init__.py
shenruqianchu_node_js_infoq_mini_shu-2024.3.1.0.dist-info/METADATA
shenruqianchu_node_js_infoq_mini_shu-2024.3.1.0.dist-info/WHEEL
shenruqianchu_node_js_infoq_mini_shu-2024.3.1.0.dist-info/entry_points.txt
shenruqianchu_node_js_infoq_mini_shu-2024.3.1.0.dist-info/top_level.txt
shenruqianchu_node_js_infoq_mini_shu-2024.3.1.0.dist-info/RECORD
